consumerdemands/__init__.py
consumerdemands/_core.py
consumerdemands/_utils.py
consumerdemands/demands.py
consumerdemands/demands_class.py
consumerdemands/engel_curves.py
consumerdemands/frischian.py
consumerdemands/hicksian.py
consumerdemands/marshallian.py
consumerdemands/root_with_precision.py
ConsumerDemands-0.4.3.dev0.dist-info/LICENSE.txt
ConsumerDemands-0.4.3.dev0.dist-info/METADATA
ConsumerDemands-0.4.3.dev0.dist-info/WHEEL
ConsumerDemands-0.4.3.dev0.dist-info/top_level.txt
ConsumerDemands-0.4.3.dev0.dist-info/RECORD
