Metadata-Version: 2.1
Name: ConsumerDemands
Version: 0.4.3.dev0
Summary: Tools for computing general demand systems from primitives.
Home-page: https://bitbucket.org/ligonresearch/demands
Author: Ethan Ligon
Author-email: ligon@berkeley.edu
License: Creative Commons Attribution-Noncommercial-ShareAlike 4.0 International license
License-File: LICENSE.txt
